{
  "variants": {
    "facing=north,lit=false": {"model": "candycraftreborn:block/advanced_sugar_factory"},
    "facing=south,lit=false": {"model": "candycraftreborn:block/advanced_sugar_factory", "y": 180},
    "facing=west,lit=false": {"model": "candycraftreborn:block/advanced_sugar_factory", "y": 270},
    "facing=east,lit=false": {"model": "candycraftreborn:block/advanced_sugar_factory", "y": 90},
    "facing=north,lit=true": {"model": "candycraftreborn:block/advanced_sugar_factory_on"},
    "facing=south,lit=true": {"model": "candycraftreborn:block/advanced_sugar_factory_on", "y": 180},
    "facing=west,lit=true": {"model": "candycraftreborn:block/advanced_sugar_factory_on", "y": 270},
    "facing=east,lit=true": {"model": "candycraftreborn:block/advanced_sugar_factory_on", "y": 90}
  }
}
